Arch_Project.srcs/sources_1/new/src/fpu_addsub.v
`timescale 1ns / 1ps
module fpu_addsub (
    input  [31:0] op_a,
    input  [31:0] op_b,
    input         op_sel,       // 0 = add, 1 = sub
    input         mode_fp,      // 0 = half (16-bit), 1 = single (32-bit)
    input         round_mode,   // 0 = nearest even, 1 = toward +∞
    output reg [31:0] result,
    output reg [4:0]  flags      // {overflow, underflow, div0, invalid, inexact}
);

    // ===== Constantes =====
    localparam SINGLE_EXP_BITS  = 8;
    localparam SINGLE_FRAC_BITS = 23;
    localparam SINGLE_BIAS      = 127;
    localparam HALF_EXP_BITS    = 5;
    localparam HALF_FRAC_BITS   = 10;
    localparam HALF_BIAS        = 15;

    // ===== Variables internas =====
    reg [7:0] exp_diff;
    reg [26:0] mant_a_shifted, mant_b_shifted;
    reg [27:0] mant_res;
    reg [7:0] exp_res;
    reg sign_res;
    reg guard, round_bit, sticky;
    reg [23:0] mant_final;
    reg effective_sub;
    reg sign_zero;
    integer shift_count;

    // ===== Preparación de operandos según modo =====
    wire [31:0] a_val = (mode_fp) ? op_a : {16'b0, op_a[15:0]};
    wire [31:0] b_val = (mode_fp) ? op_b : {16'b0, op_b[15:0]};

    wire sign_a = mode_fp ? a_val[31] : a_val[15];
    wire sign_b = mode_fp ? b_val[31] : b_val[15];

    wire [7:0] exp_a = mode_fp ? a_val[30:23] : {3'b000, a_val[14:10]};
    wire [7:0] exp_b = mode_fp ? b_val[30:23] : {3'b000, b_val[14:10]};

    wire [22:0] frac_a = mode_fp ? a_val[22:0] : {a_val[9:0], 13'b0};
    wire [22:0] frac_b = mode_fp ? b_val[22:0] : {b_val[9:0], 13'b0};

    // Mantisa con bit implícito (solo si NO es denormal)
    wire [23:0] mant_a = (exp_a == 0) ? {1'b0, frac_a} : {1'b1, frac_a};
    wire [23:0] mant_b = (exp_b == 0) ? {1'b0, frac_b} : {1'b1, frac_b};

    // ===== Casos especiales =====
    wire [7:0] exp_max = mode_fp ? 8'hFF : 8'h1F;
    wire is_nan_a  = (exp_a == exp_max && frac_a != 0);
    wire is_nan_b  = (exp_b == exp_max && frac_b != 0);
    wire is_inf_a  = (exp_a == exp_max && frac_a == 0);
    wire is_inf_b  = (exp_b == exp_max && frac_b == 0);
    wire is_zero_a = (exp_a == 0 && frac_a == 0);
    wire is_zero_b = (exp_b == 0 && frac_b == 0);

    always @(*) begin
        // ===== Inicialización =====
        flags = 5'b00000;
        result = 32'b0;
        exp_diff = 8'b0;
        mant_a_shifted = 27'b0;
        mant_b_shifted = 27'b0;
        mant_res = 28'b0;
        exp_res = 8'b0;
        sign_res = 1'b0;
        guard = 1'b0;
        round_bit = 1'b0;
        sticky = 1'b0;
        mant_final = 24'b0;
        effective_sub = 1'b0;
        sign_zero = 1'b0;
        shift_count = 0;

        // ===== Casos especiales =====
        if (is_nan_a || is_nan_b) begin
            result = mode_fp ? 32'h7FC00000 : 32'h00007E00;
            flags[1] = 1'b1; // invalid
        end
        else if (is_inf_a || is_inf_b) begin
            if (is_inf_a && is_inf_b && (sign_a ^ sign_b ^ op_sel)) begin
                // Inf - Inf = NaN
                result = mode_fp ? 32'h7FC00000 : 32'h00007E00;
                flags[1] = 1'b1;
            end else begin
                if (is_inf_a)
                    result = mode_fp ? {sign_a, 8'hFF, 23'b0} : {16'b0, sign_a, 5'h1F, 10'b0};
                else
                    result = mode_fp ? {sign_b ^ op_sel, 8'hFF, 23'b0} : {16'b0, sign_b ^ op_sel, 5'h1F, 10'b0};
            end
        end
        else if (is_zero_a && is_zero_b) begin
            sign_zero = (sign_a && sign_b && !op_sel) || (sign_a && !sign_b && op_sel);
            result = mode_fp ? {sign_zero, 31'b0} : {16'b0, sign_zero, 15'b0};
        end
        else if (is_zero_a) begin
            result = mode_fp ? {sign_b ^ op_sel, exp_b, frac_b} : {16'b0, sign_b ^ op_sel, exp_b[4:0], frac_b[22:13]};
        end
        else if (is_zero_b) begin
            result = mode_fp ? {sign_a, exp_a, frac_a} : {16'b0, sign_a, exp_a[4:0], frac_a[22:13]};
        end

        // ===== Operación normal =====
        else begin
            // Alinear exponentes
            if (exp_a > exp_b) begin
                exp_diff = exp_a - exp_b;
                mant_a_shifted = {mant_a, 3'b000};
                mant_b_shifted = (exp_diff >= 27) ? 27'b0 : ({mant_b, 3'b000} >> exp_diff);
                exp_res = exp_a;
                sign_res = sign_a;
            end else if (exp_b > exp_a) begin
                exp_diff = exp_b - exp_a;
                mant_b_shifted = {mant_b, 3'b000};
                mant_a_shifted = (exp_diff >= 27) ? 27'b0 : ({mant_a, 3'b000} >> exp_diff);
                exp_res = exp_b;
                sign_res = sign_b ^ op_sel;
            end else begin
                mant_a_shifted = {mant_a, 3'b000};
                mant_b_shifted = {mant_b, 3'b000};
                exp_res = exp_a;
                sign_res = sign_a;
            end

            // Determinar operación efectiva
            effective_sub = (sign_a ^ sign_b ^ op_sel);

            if (!effective_sub)
                mant_res = {1'b0, mant_a_shifted} + {1'b0, mant_b_shifted};
            else begin
                if (mant_a_shifted >= mant_b_shifted) begin
                    mant_res = {1'b0, mant_a_shifted} - {1'b0, mant_b_shifted};
                    sign_res = sign_a;
                end else begin
                    mant_res = {1'b0, mant_b_shifted} - {1'b0, mant_a_shifted};
                    sign_res = sign_b ^ op_sel;
                end
            end

            // ===== Normalización =====
            if (mant_res == 0) begin
                result = 32'h00000000;
                flags[3] = 1'b1; // underflow
            end else begin
                if (mant_res[27]) begin
                    mant_res = mant_res >> 1;
                    exp_res = exp_res + 1;
                end else if (!mant_res[26]) begin
                    shift_count = 0;
                    while (!mant_res[26] && mant_res != 0 && exp_res > 0 && shift_count < 27) begin
                        mant_res = mant_res << 1;
                        exp_res = exp_res - 1;
                        shift_count = shift_count + 1;
                    end
                end

                // Guard, round, sticky
                guard = mant_res[2];
                round_bit = mant_res[1];
                sticky = mant_res[0];
                mant_final = mant_res[26:3];

                // ===== Redondeo =====
                flags[0] = 0; // inexact
                case (round_mode)
                    1'b0: if (guard && (round_bit || sticky || mant_final[0])) begin
                              mant_final = mant_final + 1'b1;
                              flags[0] = 1'b1;
                          end
                    1'b1: if (!sign_res && (guard || round_bit || sticky)) begin
                              mant_final = mant_final + 1'b1;
                              flags[0] = 1'b1;
                          end
                endcase

                // Handle mantissa overflow before it wraps exp_res
if (mant_final[23]) begin
    if (exp_res >= 8'hFE) begin
        // would overflow exponent → Infinity
        exp_res = 8'hFF;
        mant_final = 24'b0;
    end else begin
        mant_final = mant_final >> 1;
        exp_res = exp_res + 1;
    end
end

                
                // ===== Overflow / Underflow y resultado =====
                if (mode_fp) begin
                    if (exp_res >= 8'hFF) begin
                        flags[4] = 1'b1; // overflow
                        result = {sign_res, 8'hFF, 23'b0}; // +Inf / -Inf
                    end else if (exp_res == 0) begin
                        flags[3] = 1'b1; // underflow
    result = {sign_res, exp_res[7:0], mant_final[22:0]};
                    end else begin
                        result = {sign_res, exp_res[7:0], mant_final[22:0]};
                    end
                end else begin
                    if (exp_res >= 8'h1F) begin
                        flags[4] = 1'b1; // overflow
                        result = {16'b0, sign_res, 5'h1F, 10'b0};
                    end else if (exp_res == 0) begin
                        flags[3] = 1'b1; // underflow
    result = {sign_res, exp_res[7:0], mant_final[22:0]};
                    end else begin
                        result = {16'b0, sign_res, exp_res[4:0], mant_final[22:13]};
                    end
                end
            end
        end
    end
endmodule

Arch_Project.srcs/sources_1/new/tb/tb_addsub.v
`timescale 1ns / 1ns

module tb_fpu_addsub();

    // Señales del DUT
    reg [31:0] op_a, op_b;
    reg op_sel, mode_fp, round_mode;
    wire [31:0] result;
    wire [4:0] flags;

    // Instancia del módulo
    fpu_addsub uut (
        .op_a(op_a),
        .op_b(op_b),
        .op_sel(op_sel),
        .mode_fp(mode_fp),
        .round_mode(round_mode),
        .result(result),
        .flags(flags)
    );

    integer test_num = 0;
    integer pass_count = 0;

    // Task para mostrar resultados y verificar
    task display_test;
        input [127:0] desc;
        input [31:0] expected_result;
        input [4:0]  expected_flags;
        begin
            test_num = test_num + 1;
            $display("\n=== Test %0d: %s ===", test_num, desc);
            $display("Mode: %s | Op: %s | Round: %s", 
                     mode_fp ? "SINGLE" : "HALF",
                     op_sel ? "SUB" : "ADD",
                     round_mode ? "+INF" : "NEAR");
            $display("A = %h | B = %h", op_a, op_b);
            #5;
            $display("Result = %h | Expected = %h", result, expected_result);
            $display("Flags  = %b | Expected = %b", flags, expected_flags);
            if (result === expected_result && flags === expected_flags) begin
                $display("PASS");
                pass_count = pass_count + 1;
            end else begin
                $display("FAIL");
            end
        end
    endtask

    initial begin
        $dumpfile("addsub_floating.vcd");
        $dumpvars(0, tb_fpu_addsub);

        $display("======================================");
        $display("   FPU ADD/SUB TESTBENCH");
        $display("======================================");

        // =========================
        // TESTS DEFINIDOS
        // =========================
        // SINGLE PRECISION
        mode_fp = 1;
        round_mode = 0;
        
        op_sel = 0; op_a = 32'h3F800000; op_b = 32'h40000000; display_test("1.0 + 2.0", 32'h40e00000, 5'b00000);
        op_sel = 1; op_a = 32'h40A00000; op_b = 32'h40400000; display_test("5.0 - 3.0", 32'h40c00000, 5'b00000);
        op_sel = 0; op_a = 32'h3F800000; op_b = 32'h3F000000; display_test("1.0 + 0.5", 32'h40600000, 5'b00000);
        op_sel = 1; op_a = 32'h40200000; op_b = 32'h40200000; display_test("2.5 - 2.5", 32'h00000000, 5'b01000);
        op_sel = 0; op_a = 32'hBF800000; op_b = 32'hC0000000; display_test("-1.0 + -2.0", 32'hC0E00000, 5'b00000);
        op_sel = 0; op_a = 32'h40400000; op_b = 32'hBF800000; display_test("3.0 + -1.0", 32'h40C00000, 5'b00000);
        op_sel = 0; op_a = 32'h7FC00000; op_b = 32'h3F800000; display_test("NaN + 1.0", 32'h7FC00000, 5'b00010);
        op_sel = 0; op_a = 32'h7F800000; op_b = 32'h40000000; display_test("+Inf + 2.0", 32'h7F800000, 5'b00000);
        op_sel = 1; op_a = 32'h7F800000; op_b = 32'h7F800000; display_test("+Inf - +Inf", 32'h7FC00000, 5'b00010);
        op_sel = 0; op_a = 32'h00000000; op_b = 32'h00000000; display_test("0.0 + 0.0", 32'h00000000, 5'b00000);
        op_sel = 0; round_mode = 1; op_a = 32'h3F800000; op_b = 32'h33800000; display_test("Rounding toward +Inf", 32'h40400000, 5'b00001);
        op_sel = 0; round_mode = 0; op_a = 32'h7F000000; op_b = 32'h7F000000; display_test("Overflow test", 32'h7F800000, 5'b10000);

        // HALF PRECISION
        mode_fp = 0; round_mode = 0;
        op_sel = 0; op_a = 32'h00003C00; op_b = 32'h00004000; display_test("HALF 1.0 + 2.0", 32'h00004700, 5'b00000);
        op_sel = 1; op_a = 32'h00004200; op_b = 32'h00003C00; display_test("HALF 3.0 - 1.0", 32'h00004600, 5'b00000);
        op_sel = 0; op_a = 32'h00003C00; op_b = 32'h00003800; display_test("HALF 1.0 + 0.5", 32'h00004300, 5'b00000);
        op_sel = 0; op_a = 32'h0000BC00; op_b = 32'h0000C000; display_test("HALF -1.0 + -2.0", 32'h0000C700, 5'b00000);
        op_sel = 0; op_a = 32'h00007E00; op_b = 32'h00003C00; display_test("HALF NaN + 1.0", 32'h00007E00, 5'b00010);
        op_sel = 0; op_a = 32'h00007C00; op_b = 32'h00004000; display_test("HALF +Inf + 2.0", 32'h00007C00, 5'b00000);
        op_sel = 0; round_mode = 1; op_a = 32'h00003C00; op_b = 32'h00000400; display_test("HALF Rounding toward +Inf", 32'h00004200, 5'b00000);
        op_sel = 0; round_mode = 0; op_a = 32'h00000400; op_b = 32'h00000400; display_test("HALF Underflow test", 32'h00000E00, 5'b00000);

        // CORNER CASES SINGLE
        mode_fp = 1; round_mode = 0;
        op_sel = 0; op_a = 32'h00000001; op_b = 32'h00000001; display_test("SINGLE Denormal + Denormal", 32'h00000002, 5'b01000);
        op_sel = 0; op_a = 32'h7F7FFFFF; op_b = 32'h00800000; display_test("SINGLE Max + Min", 32'h7F800000, 5'b10000);
        op_sel = 1; op_a = 32'h3F800000; op_b = 32'h40000000; display_test("SINGLE 1.0 - 2.0 = -1.0", 32'hC0400000, 5'b00000);
        op_sel = 1; op_a = 32'h3F800000; op_b = 32'h34000000; display_test("SINGLE Nearest even edge", 32'h3FFFFFFF, 5'b00000);

        $display("\n======================================");
        $display("Tests completados: %0d / 24", pass_count);
        $display("======================================");
        $finish;
    end

endmodule

Arch_Project.sim/sim_1/behav/xsim/addsub_floating.vcd
$date
   Fri Oct 10 09:32:39 2025
$end

$version
  2025.1.0
  $dumpfile ("addsub_floating.vcd") 
$end

$timescale
  1ps
$end

$scope module tb_fpu_addsub $end
$var reg 32 ! op_a [31:0] $end
$var reg 32 " op_b [31:0] $end
$var reg 1 # op_sel $end
$var reg 1 $ mode_fp $end
$var reg 1 % round_mode $end
$var wire 32 & result [31:0] $end
$var wire 5 ' flags [4:0] $end
$var integer 32 ( test_num [31:0] $end
$var integer 32 ) pass_count [31:0] $end
$scope module uut $end
$var wire 32 * op_a [31:0] $end
$var wire 32 + op_b [31:0] $end
$var wire 1 , op_sel $end
$var wire 1 - mode_fp $end
$var wire 1 . round_mode $end
$var reg 32 / result [31:0] $end
$var reg 5 0 flags [4:0] $end
$var reg 8 1 exp_diff [7:0] $end
$var reg 27 2 mant_a_shifted [26:0] $end
$var reg 27 3 mant_b_shifted [26:0] $end
$var reg 28 4 mant_res [27:0] $end
$var reg 8 5 exp_res [7:0] $end
$var reg 1 6 sign_res $end
$var reg 1 7 guard $end
$var reg 1 8 round_bit $end
$var reg 1 9 sticky $end
$var reg 24 : mant_final [23:0] $end
$var reg 1 ; effective_sub $end
$var reg 1 < sign_zero $end
$var integer 32 = shift_count [31:0] $end
$var wire 32 > a_val [31:0] $end
$var wire 32 ? b_val [31:0] $end
$var wire 1 @ sign_a $end
$var wire 1 A sign_b $end
$var wire 8 B exp_a [7:0] $end
$var wire 8 C exp_b [7:0] $end
$var wire 23 D frac_a [22:0] $end
$var wire 23 E frac_b [22:0] $end
$var wire 24 F mant_a [23:0] $end
$var wire 24 G mant_b [23:0] $end
$var wire 8 H exp_max [7:0] $end
$var wire 1 I is_nan_a $end
$var wire 1 J is_nan_b $end
$var wire 1 K is_inf_a $end
$var wire 1 L is_inf_b $end
$var wire 1 M is_zero_a $end
$var wire 1 N is_zero_b $end
$upscope $end
$scope task display_test $end
$var reg 128 O desc [127:0] $end
$var reg 32 P expected_result [31:0] $end
$var reg 5 Q expected_flags [4:0] $end
$upscope $end
$upscope $end
$enddefinitions $end

#0
$dumpvars
b111111100000000000000000000000 !
b1000000000000000000000000000000 "
0#
1$
0%
b1000000111000000000000000000000 &
b0 '
b1 (
b0 )
b111111100000000000000000000000 *
b1000000000000000000000000000000 +
0,
1-
0.
b1000000111000000000000000000000 /
b0 0
b1 1
b10000000000000000000000000 2
b100000000000000000000000000 3
b110000000000000000000000000 4
b10000001 5
06
07
08
09
b11000000000000000000000 :
0;
0<
b0 =
b111111100000000000000000000000 >
b1000000000000000000000000000000 ?
0@
0A
b1111111 B
b10000000 C
b0 D
b0 E
b100000000000000000000000 F
b100000000000000000000000 G
b11111111 H
0I
0J
0K
0L
0M
0N
b1100010010111000110000001000000010101100100000001100100010111000110000 O
b1000000111000000000000000000000 P
b0 Q
$end

#5000
b1000000101000000000000000000000 !
b1000000010000000000000000000000 "
1#
b1000000110000000000000000000000 &
b10 (
b1 )
b1000000101000000000000000000000 *
b1000000010000000000000000000000 +
1,
b1000000110000000000000000000000 /
b1 1
b101000000000000000000000000 2
b11000000000000000000000000 3
b100000000000000000000000000 4
b10000001 5
b10000000000000000000000 :
1;
b1 =
b1000000101000000000000000000000 >
b1000000010000000000000000000000 ?
b10000001 B
b1000000000000000000000 D
b10000000000000000000000 E
b101000000000000000000000 F
b110000000000000000000000 G
b1101010010111000110000001000000010110100100000001100110010111000110000 O
b1000000110000000000000000000000 P

#10000
b111111100000000000000000000000 !
b111111000000000000000000000000 "
0#
b1000000011000000000000000000000 &
b11 (
b10 )
b111111100000000000000000000000 *
b111111000000000000000000000000 +
0,
b1000000011000000000000000000000 /
b1 1
b100000000000000000000000000 2
b10000000000000000000000000 3
b110000000000000000000000000 4
b10000000 5
b11000000000000000000000 :
0;
b0 =
b111111100000000000000000000000 >
b111111000000000000000000000000 ?
b1111111 B
b1111110 C
b0 D
b0 E
b100000000000000000000000 F
b100000000000000000000000 G
b1100010010111000110000001000000010101100100000001100000010111000110101 O
b1000000011000000000000000000000 P

#15000
b1000000001000000000000000000000 !
b1000000001000000000000000000000 "
1#
b0 &
b1000 '
b100 (
b11 )
b1000000001000000000000000000000 *
b1000000001000000000000000000000 +
1,
b0 /
b1000 0
b0 1
b101000000000000000000000000 2
b101000000000000000000000000 3
b0 4
b10000000 5
b0 :
1;
b1000000001000000000000000000000 >
b1000000001000000000000000000000 ?
b10000000 B
b10000000 C
b1000000000000000000000 D
b1000000000000000000000 E
b101000000000000000000000 F
b101000000000000000000000 G
b1100100010111000110101001000000010110100100000001100100010111000110101 O
b0 P
b1000 Q

#20000
b10111111100000000000000000000000 !
b11000000000000000000000000000000 "
0#
b11000000111000000000000000000000 &
b0 '
b101 (
b100 )
b10111111100000000000000000000000 *
b11000000000000000000000000000000 +
0,
b11000000111000000000000000000000 /
b0 0
b1 1
b10000000000000000000000000 2
b100000000000000000000000000 3
b110000000000000000000000000 4
b10000001 5
16
b11000000000000000000000 :
0;
b10111111100000000000000000000000 >
b11000000000000000000000000000000 ?
1@
1A
b1111111 B
b0 D
b0 E
b100000000000000000000000 F
b100000000000000000000000 G
b10110100110001001011100011000000100000001010110010000000101101001100100010111000110000 O
b11000000111000000000000000000000 P
b0 Q

#25000
b1000000010000000000000000000000 !
b10111111100000000000000000000000 "
b1000000110000000000000000000000 &
b110 (
b101 )
b1000000010000000000000000000000 *
b10111111100000000000000000000000 +
b1000000110000000000000000000000 /
b1 1
b110000000000000000000000000 2
b10000000000000000000000000 3
b100000000000000000000000000 4
b10000001 5
06
b10000000000000000000000 :
1;
b1000000010000000000000000000000 >
b10111111100000000000000000000000 ?
0@
b10000000 B
b1111111 C
b10000000000000000000000 D
b110000000000000000000000 F
b110011001011100011000000100000001010110010000000101101001100010010111000110000 O
b1000000110000000000000000000000 P

#30000
b1111111110000000000000000000000 !
b111111100000000000000000000000 "
b1111111110000000000000000000000 &
b10 '
b111 (
b110 )
b1111111110000000000000000000000 *
b111111100000000000000000000000 +
b1111111110000000000000000000000 /
b10 0
b0 1
b0 2
b0 3
b0 4
b0 5
b0 :
0;
b1111111110000000000000000000000 >
b111111100000000000000000000000 ?
0A
b11111111 B
1I
b10011100110000101001110001000000010101100100000001100010010111000110000 O
b1111111110000000000000000000000 P
b10 Q

#35000
b1111111100000000000000000000000 !
b1000000000000000000000000000000 "
b1111111100000000000000000000000 &
b0 '
b1000 (
b111 )
b1111111100000000000000000000000 *
b1000000000000000000000000000000 +
b1111111100000000000000000000000 /
b0 0
b1111111100000000000000000000000 >
b1000000000000000000000000000000 ?
b10000000 C
b0 D
b100000000000000000000000 F
0I
1K
b101011010010010110111001100110001000000010101100100000001100100010111000110000 O
b1111111100000000000000000000000 P
b0 Q

#40000
b1111111100000000000000000000000 "
1#
b1111111110000000000000000000000 &
b10 '
b1001 (
b1000 )
b1111111100000000000000000000000 +
1,
b1111111110000000000000000000000 /
b10 0
b1111111100000000000000000000000 ?
b11111111 C
1L
b10101101001001011011100110011000100000001011010010000000101011010010010110111001100110 O
b1111111110000000000000000000000 P
b10 Q

#45000
b0 !
b0 "
0#
b0 &
b0 '
b1010 (
b1001 )
b0 *
b0 +
0,
b0 /
b0 0
b0 >
b0 ?
b0 B
b0 C
b0 F
b0 G
0K
0L
1M
1N
b1100000010111000110000001000000010101100100000001100000010111000110000 O
b0 P
b0 Q

#50000
b111111100000000000000000000000 !
b110011100000000000000000000000 "
1%
b1000000010000000000000000000000 &
b1 '
b1011 (
b1010 )
b111111100000000000000000000000 *
b110011100000000000000000000000 +
1.
b1000000010000000000000000000000 /
b1 0
b11000 1
b100000000000000000000000000 2
b100 3
b100000000000000000000000100 4
b10000000 5
17
b10000000000000000000000 :
b111111100000000000000000000000 >
b110011100000000000000000000000 ?
b1111111 B
b1100111 C
b100000000000000000000000 F
b100000000000000000000000 G
0M
0N
b1100100011010010110111001100111001000000111010001101111011101110110000101110010011001000010000000101011010010010110111001100110 O
b1000000010000000000000000000000 P
b1 Q

#55000
b1111111000000000000000000000000 !
b1111111000000000000000000000000 "
0%
b1111111100000000000000000000000 &
b10000 '
b1100 (
b1011 )
b1111111000000000000000000000000 *
b1111111000000000000000000000000 +
0.
b1111111100000000000000000000000 /
b10000 0
b0 1
b100000000000000000000000000 2
b100000000000000000000000000 3
b100000000000000000000000000 4
b11111111 5
07
b0 :
b1111111000000000000000000000000 >
b1111111000000000000000000000000 ?
b11111110 B
b11111110 C
b1001111011101100110010101110010011001100110110001101111011101110010000001110100011001010111001101110100 O
b1111111100000000000000000000000 P
b10000 Q

#60000
b11110000000000 !
b100000000000000 "
0$
b100011100000000 &
b0 '
b1101 (
b1100 )
b11110000000000 *
b100000000000000 +
0-
b100011100000000 /
b0 0
b1 1
b10000000000000000000000000 2
b100000000000000000000000000 3
b110000000000000000000000000 4
b10001 5
b11000000000000000000000 :
b11110000000000 >
b100000000000000 ?
b1111 B
b10000 C
b11111 H
b100100001000001010011000100011000100000001100010010111000110000001000000010101100100000001100100010111000110000 O
b100011100000000 P
b0 Q

#65000
b100001000000000 !
b11110000000000 "
1#
b100011000000000 &
b1110 (
b1101 )
b100001000000000 *
b11110000000000 +
1,
b100011000000000 /
b1 1
b110000000000000000000000000 2
b10000000000000000000000000 3
b100000000000000000000000000 4
b10001 5
b10000000000000000000000 :
1;
b100001000000000 >
b11110000000000 ?
b10000 B
b1111 C
b10000000000000000000000 D
b110000000000000000000000 F
b100100001000001010011000100011000100000001100110010111000110000001000000010110100100000001100010010111000110000 O
b100011000000000 P

#70000
b11110000000000 !
b11100000000000 "
0#
b100001100000000 &
b1111 (
b1110 )
b11110000000000 *
b11100000000000 +
0,
b100001100000000 /
b1 1
b100000000000000000000000000 2
b10000000000000000000000000 3
b110000000000000000000000000 4
b10000 5
b11000000000000000000000 :
0;
b11110000000000 >
b11100000000000 ?
b1111 B
b1110 C
b0 D
b100000000000000000000000 F
b100100001000001010011000100011000100000001100010010111000110000001000000010101100100000001100000010111000110101 O
b100001100000000 P

#75000
b1011110000000000 !
b1100000000000000 "
b1100011100000000 &
b10000 (
b1111 )
b1011110000000000 *
b1100000000000000 +
b1100011100000000 /
b1 1
b10000000000000000000000000 2
b100000000000000000000000000 3
b110000000000000000000000000 4
b10001 5
16
b11000000000000000000000 :
b1011110000000000 >
b1100000000000000 ?
1@
1A
b10000 C
b1001000010000010100110001000110001000000010110100110001001011100011000000100000001010110010000000101101001100100010111000110000 O
b1100011100000000 P

#80000
b111111000000000 !
b11110000000000 "
b111111000000000 &
b10 '
b10001 (
b10000 )
b111111000000000 *
b11110000000000 +
b111111000000000 /
b10 0
b0 1
b0 2
b0 3
b0 4
b0 5
06
b0 :
b111111000000000 >
b11110000000000 ?
0@
0A
b11111 B
b1111 C
b10000000000000000000000 D
b110000000000000000000000 F
1I
b100100001000001010011000100011000100000010011100110000101001110001000000010101100100000001100010010111000110000 O
b111111000000000 P
b10 Q

#85000
b111110000000000 !
b100000000000000 "
b111110000000000 &
b0 '
b10010 (
b10001 )
b111110000000000 *
b100000000000000 +
b111110000000000 /
b0 0
b111110000000000 >
b100000000000000 ?
b10000 C
b0 D
b100000000000000000000000 F
0I
1K
b10010000100000101001100010001100010000000101011010010010110111001100110001000000010101100100000001100100010111000110000 O
b111110000000000 P
b0 Q

#90000
b11110000000000 !
b10000000000 "
1%
b100001000000000 &
b10011 (
b10010 )
b11110000000000 *
b10000000000 +
1.
b100001000000000 /
b1110 1
b100000000000000000000000000 2
b1000000000000 3
b100000000000001000000000000 4
b10000 5
b10000000000000100000000 :
b11110000000000 >
b10000000000 ?
b1111 B
b1 C
0K
b1100100011010010110111001100111001000000111010001101111011101110110000101110010011001000010000000101011010010010110111001100110 O
b100001000000000 P

#95000
b10000000000 !
0%
b111000000000 &
b10100 (
b10011 )
b10000000000 *
0.
b111000000000 /
b0 1
b100000000000000000000000000 2
b100000000000000000000000000 3
b100000000000000000000000000 4
b11 5
b10000000000000000000000 :
b10000000000 >
b1 B
b1000110001000000101010101101110011001000110010101110010011001100110110001101111011101110010000001110100011001010111001101110100 O
b111000000000 P

#100000
b1 !
b1 "
1$
b10 &
b1000 '
b10101 (
b10100 )
b1 *
b1 +
1-
b10 /
b1000 0
b1000 2
b1000 3
b10000 4
b0 5
b10 :
b1 >
b1 ?
b0 B
b0 C
b1 D
b1 E
b1 F
b1 G
b11111111 H
b1101111011100100110110101100001011011000010000000101011001000000100010001100101011011100110111101110010011011010110000101101100 O
b10 P
b1000 Q

#105000
b1111111011111111111111111111111 !
b100000000000000000000000 "
b1111111100000000000000000000000 &
b10000 '
b10110 (
b10101 )
b1111111011111111111111111111111 *
b100000000000000000000000 +
b1111111100000000000000000000000 /
b10000 0
b11111101 1
b111111111111111111111111000 2
b0 3
b111111111111111111111111000 4
b11111111 5
b0 :
b1111111011111111111111111111111 >
b100000000000000000000000 ?
b11111110 B
b1 C
b11111111111111111111111 D
b0 E
b111111111111111111111111 F
b100000000000000000000000 G
b1010011010010010100111001000111010011000100010100100000010011010110000101111000001000000010101100100000010011010110100101101110 O
b1111111100000000000000000000000 P
b10000 Q

#110000
b111111100000000000000000000000 !
b1000000000000000000000000000000 "
1#
b11000000010000000000000000000000 &
b0 '
b10111 (
b10110 )
b111111100000000000000000000000 *
b1000000000000000000000000000000 +
1,
b11000000010000000000000000000000 /
b0 0
b1 1
b10000000000000000000000000 2
b100000000000000000000000000 3
b100000000000000000000000000 4
b10000000 5
16
b10000000000000000000000 :
1;
b1 =
b111111100000000000000000000000 >
b1000000000000000000000000000000 ?
b1111111 B
b10000000 C
b0 D
b100000000000000000000000 F
b110001001011100011000000100000001011010010000000110010001011100011000000100000001111010010000000101101001100010010111000110000 O
b11000000010000000000000000000000 P
b0 Q

#115000
b110100000000000000000000000000 "
b111111111111111111111111111111 &
b11000 (
b10111 )
b110100000000000000000000000000 +
b111111111111111111111111111111 /
b10111 1
b100000000000000000000000000 2
b1000 3
b111111111111111111111110000 4
b1111111 5
06
b11111111111111111111111 :
1;
b1 =
b110100000000000000000000000000 ?
b1101000 C
b1100101011000010111001001100101011100110111010000100000011001010111011001100101011011100010000001100101011001000110011101100101 O
b111111111111111111111111111111 P

#120000
b11000 )
