Arch_Project.srcs/sources_1/new/src/fpu_addsub.v
`timescale 1ns / 1ps
module fpu_addsub (
    input  [31:0] op_a,
    input  [31:0] op_b,
    input         op_sel,       // 0 = add, 1 = sub
    input         mode_fp,      // 0 = half (16-bit), 1 = single (32-bit)
    input         round_mode,   // 0 = nearest even, 1 = toward +∞
    output reg [31:0] result,
    output reg [4:0]  flags      // {overflow, underflow, div0, invalid, inexact}
);

    // ===== Constantes =====
    localparam SINGLE_EXP_BITS  = 8;
    localparam SINGLE_FRAC_BITS = 23;
    localparam SINGLE_BIAS      = 127;
    localparam HALF_EXP_BITS    = 5;
    localparam HALF_FRAC_BITS   = 10;
    localparam HALF_BIAS        = 15;

    // ===== Preparación de operandos según modo =====
    wire [31:0] a_val = (mode_fp) ? op_a : {16'b0, op_a[15:0]};
    wire [31:0] b_val = (mode_fp) ? op_b : {16'b0, op_b[15:0]};

    wire sign_a = mode_fp ? a_val[31] : a_val[15];
    wire sign_b = mode_fp ? b_val[31] : b_val[15];

    wire [7:0] exp_a = mode_fp ? a_val[30:23] : {3'b000, a_val[14:10]};
    wire [7:0] exp_b = mode_fp ? b_val[30:23] : {3'b000, b_val[14:10]};

    wire [22:0] frac_a = mode_fp ? a_val[22:0] : {a_val[9:0], 13'b0};
    wire [22:0] frac_b = mode_fp ? b_val[22:0] : {b_val[9:0], 13'b0};

    // Mantisa con bit implícito (solo si NO es denormal)
    wire [23:0] mant_a = (exp_a == 0) ? {1'b0, frac_a} : {1'b1, frac_a};
    wire [23:0] mant_b = (exp_b == 0) ? {1'b0, frac_b} : {1'b1, frac_b};

    // ===== Casos especiales con límites dinámicos =====
    wire [7:0] exp_max = mode_fp ? 8'hFF : 8'h1F;
    
    wire is_nan_a  = (exp_a == exp_max && frac_a != 0);
    wire is_nan_b  = (exp_b == exp_max && frac_b != 0);
    wire is_inf_a  = (exp_a == exp_max && frac_a == 0);
    wire is_inf_b  = (exp_b == exp_max && frac_b == 0);
    wire is_zero_a = (exp_a == 0 && frac_a == 0);
    wire is_zero_b = (exp_b == 0 && frac_b == 0);
    
    reg effective_sub;
    wire sign_b_eff;
    
    assign sign_b_eff = sign_b ^ op_sel;

    always @(*) begin 
        flags = 5'b00000;
        result = 32'b0;

        // -------- Casos especiales --------
        if (is_nan_a || is_nan_b) begin
            result = mode_fp ? 32'h7FC00000 : 32'h00007E00;
            flags[1] = 1'b1; // invalid
        end
        else if (is_inf_a || is_inf_b) begin
            if (is_inf_a && is_inf_b && (sign_a ^ sign_b_eff)) begin
                // Inf - Inf = NaN
                result = mode_fp ? 32'h7FC00000 : 32'h00007E00;
                flags[1] = 1'b1;
            end else begin
                if (is_inf_a)
                    result = mode_fp ? {sign_a, 8'hFF, 23'b0} : {16'b0, sign_a, 5'h1F, 10'b0};
                else
                    result = mode_fp ? {sign_b_eff, 8'hFF, 23'b0} : {16'b0, sign_b_eff, 5'h1F, 10'b0};
            end
        end
        else if (is_zero_a && is_zero_b) begin: xd
            reg sign_zero;
            sign_zero = (sign_a && sign_b && !op_sel) || (sign_a && !sign_b && op_sel);
            result = mode_fp ? {sign_zero, 31'b0} : {16'b0, sign_zero, 15'b0};
        end
        else if (is_zero_a) begin
            result = mode_fp ? {sign_b_eff, exp_b, frac_b} : {16'b0, sign_b_eff, exp_b[4:0], frac_b[22:13]};
        end
        else if (is_zero_b) begin
            result = mode_fp ? {sign_a, exp_a, frac_a} : {16'b0, sign_a, exp_a[4:0], frac_a[22:13]};
        end
        // -------- Operación normal --------
        else begin: xd2
            reg [7:0] exp_diff;
            reg [26:0] mant_a_shifted, mant_b_shifted;
            reg [27:0] mant_res;
            reg [7:0] exp_res;
            reg sign_res;
            reg guard, round_bit, sticky;
            reg [23:0] mant_final;
            integer shift_count;

            // === 1. Determinar operación efectiva ===
            effective_sub = (sign_a != sign_b_eff);

            // === 2. Alinear exponentes ===
            if (exp_a > exp_b) begin
                exp_diff = exp_a - exp_b;
                mant_a_shifted = {mant_a, 3'b000};
                if (exp_diff >= 27)
                    mant_b_shifted = 27'b0;
                else
                    mant_b_shifted = ({mant_b, 3'b000} >> exp_diff);
                exp_res = exp_a;
                sign_res = sign_a;
            end else if (exp_b > exp_a) begin
                exp_diff = exp_b - exp_a;
                if (exp_diff >= 27)
                    mant_a_shifted = 27'b0;
                else
                    mant_a_shifted = ({mant_a, 3'b000} >> exp_diff);
                mant_b_shifted = {mant_b, 3'b000};
                exp_res = exp_b;
                sign_res = sign_b_eff;
            end else begin
                mant_a_shifted = {mant_a, 3'b000};
                mant_b_shifted = {mant_b, 3'b000};
                exp_res = exp_a;
                // Si exponentes iguales, en resta el signo depende de cuál mantisa es mayor
                if (effective_sub && mant_b > mant_a)
                    sign_res = sign_b_eff;
                else
                    sign_res = sign_a;
            end

            // === 3. Suma o resta efectiva ===
            if (!effective_sub) begin
                mant_res = {1'b0, mant_a_shifted} + {1'b0, mant_b_shifted};
            end else begin
                if (mant_a_shifted >= mant_b_shifted) begin
                    mant_res = {1'b0, mant_a_shifted} - {1'b0, mant_b_shifted};
                    sign_res = sign_a;
                end else begin
                    mant_res = {1'b0, mant_b_shifted} - {1'b0, mant_a_shifted};
                    sign_res = sign_b_eff;
                end
            end

            // === 4. Normalización ===
            if (mant_res == 0) begin
                result = mode_fp ? 32'h00000000 : 32'h00000000;
                flags[3] = 1'b1; // underflow
            end else begin
                // Shift derecha si hay overflow (bit 27 set)
                if (mant_res[27]) begin
                    mant_res = mant_res >> 1;
                    exp_res = exp_res + 1;
                end 
                // Shift izquierda hasta que bit 26 esté en 1
                else begin
                    shift_count = 0;
                    while (!mant_res[26] && mant_res != 0 && exp_res > 1 && shift_count < 27) begin
                        mant_res = mant_res << 1;
                        exp_res = exp_res - 1;
                        shift_count = shift_count + 1;
                    end
                end

                // Extraer bits de redondeo ANTES de tomar la mantisa
                // La mantisa normalizada debe tener el bit implícito en posición 26
                // Tomamos bits 25:3 para obtener los 23 bits de fracción
                // y bits 2:0 para redondeo (guard, round, sticky)
                guard = mant_res[2];
                round_bit = mant_res[1];
                sticky = mant_res[0];
                mant_final = {1'b0, mant_res[25:3]};

                // === 5. Redondeo ===
                flags[0] = 0;
                case(round_mode)
                    1'b0: begin // Round to nearest even
                        if (guard && (round_bit || sticky || mant_final[0])) begin
                            mant_final = mant_final + 1'b1;
                            flags[0] = 1'b1;
                        end
                    end
                    1'b1: begin // Round toward +∞
                        if (!sign_res && (guard || round_bit || sticky)) begin
                            mant_final = mant_final + 1'b1;
                            flags[0] = 1'b1;
                        end
                    end
                endcase

                // Si redondeo causó overflow en la mantisa
                if (mant_final[23]) begin
                    mant_final = mant_final >> 1;
                    exp_res = exp_res + 1;
                end

                // === 6. Verificar overflow/underflow y construir resultado ===
                if (mode_fp) begin
                    if (exp_res >= 8'hFF) begin
                        // Overflow: retornar infinito
                        flags[4] = 1'b1;
                        result = {sign_res, 8'hFF, 23'b0};
                    end else if (exp_res == 0) begin
                        // Underflow: retornar cero o denormal
                        flags[3] = 1'b1;
                        result = {sign_res, 8'h00, mant_final[22:0]};
                    end else begin
                        result = {sign_res, exp_res, mant_final[22:0]};
                    end
                end else begin
                    if (exp_res >= 8'h1F) begin
                        flags[4] = 1'b1;
                        result = {16'b0, sign_res, 5'h1F, 10'b0};
                    end else if (exp_res == 0) begin
                        flags[3] = 1'b1;
                        result = {16'b0, sign_res, 5'h00, mant_final[22:13]};
                    end else begin
                        result = {16'b0, sign_res, exp_res[4:0], mant_final[22:13]};
                    end
                end
            end
        end
    end
endmodule

Arch_Project.srcs/sources_1/new/tb/tb_addsub.v
`timescale 1ns / 1ns

module tb_fpu_addsub();

    // Señales del DUT
    reg [31:0] op_a, op_b;
    reg op_sel, mode_fp, round_mode;
    wire [31:0] result;
    wire [4:0] flags;

    // Instancia del módulo
    fpu_addsub uut (
        .op_a(op_a),
        .op_b(op_b),
        .op_sel(op_sel),
        .mode_fp(mode_fp),
        .round_mode(round_mode),
        .result(result),
        .flags(flags)
    );

    integer test_num = 0;
    integer pass_count = 0;
    integer fail_count = 0;

    // ==========================================
    // FUNCIONES DE CONVERSIÓN FLOAT <-> REAL
    // ==========================================
    
    // Convierte float32 a real
    function real fp32_to_real;
        input [31:0] fp;
        reg sign;
        reg [7:0] exp;
        reg [22:0] frac;
        real mant;
        integer exp_val;
        begin
            sign = fp[31];
            exp = fp[30:23];
            frac = fp[22:0];
            
            // Casos especiales
            if (exp == 8'hFF) begin
                if (frac != 0)
                    fp32_to_real = 0.0/0.0; // NaN
                else if (sign)
                    fp32_to_real = -1.0/0.0; // -Inf
                else
                    fp32_to_real = 1.0/0.0; // +Inf
            end
            else if (exp == 0 && frac == 0) begin
                fp32_to_real = sign ? -0.0 : 0.0;
            end
            else begin
                // Normal o denormal
                if (exp == 0)
                    mant = $itor(frac) / $pow(2.0, 23.0);
                else
                    mant = 1.0 + $itor(frac) / $pow(2.0, 23.0);
                
                exp_val = exp - 127;
                fp32_to_real = mant * $pow(2.0, $itor(exp_val));
                if (sign) fp32_to_real = -fp32_to_real;
            end
        end
    endfunction

    // Convierte float16 a real
    function real fp16_to_real;
        input [15:0] fp;
        reg sign;
        reg [4:0] exp;
        reg [9:0] frac;
        real mant;
        integer exp_val;
        begin
            sign = fp[15];
            exp = fp[14:10];
            frac = fp[9:0];
            
            if (exp == 5'h1F) begin
                if (frac != 0)
                    fp16_to_real = 0.0/0.0; // NaN
                else if (sign)
                    fp16_to_real = -1.0/0.0; // -Inf
                else
                    fp16_to_real = 1.0/0.0; // +Inf
            end
            else if (exp == 0 && frac == 0) begin
                fp16_to_real = sign ? -0.0 : 0.0;
            end
            else begin
                if (exp == 0)
                    mant = $itor(frac) / $pow(2.0, 10.0);
                else
                    mant = 1.0 + $itor(frac) / $pow(2.0, 10.0);
                
                exp_val = exp - 15;
                fp16_to_real = mant * $pow(2.0, $itor(exp_val));
                if (sign) fp16_to_real = -fp16_to_real;
            end
        end
    endfunction

    // Convierte real a float32
    function [31:0] real_to_fp32;
        input real val;
        reg sign;
        reg [7:0] exp;
        reg [22:0] frac;
        real abs_val, mant;
        integer exp_val;
        begin
            if (val != val) begin // NaN
                real_to_fp32 = 32'h7FC00000;
            end
            else if (val == 1.0/0.0) begin // +Inf
                real_to_fp32 = 32'h7F800000;
            end
            else if (val == -1.0/0.0) begin // -Inf
                real_to_fp32 = 32'hFF800000;
            end
            else if (val == 0.0) begin
                real_to_fp32 = 32'h00000000;
            end
            else begin
                sign = (val < 0);
                abs_val = sign ? -val : val;
                
                // Calcular exponente
                exp_val = 0;
                mant = abs_val;
                while (mant >= 2.0) begin
                    mant = mant / 2.0;
                    exp_val = exp_val + 1;
                end
                while (mant < 1.0 && exp_val > -126) begin
                    mant = mant * 2.0;
                    exp_val = exp_val - 1;
                end
                
                // Manejar underflow
                if (exp_val < -126) begin
                    real_to_fp32 = {sign, 31'b0};
                end
                // Manejar overflow
                else if (exp_val > 127) begin
                    real_to_fp32 = sign ? 32'hFF800000 : 32'h7F800000;
                end
                else begin
                    exp = exp_val + 127;
                    frac = $rtoi((mant - 1.0) * $pow(2.0, 23.0));
                    real_to_fp32 = {sign, exp, frac};
                end
            end
        end
    endfunction

    // Convierte real a float16
    function [31:0] real_to_fp16;
        input real val;
        reg sign;
        reg [4:0] exp;
        reg [9:0] frac;
        real abs_val, mant;
        integer exp_val;
        begin
            if (val != val) begin
                real_to_fp16 = 32'h00007E00;
            end
            else if (val == 1.0/0.0) begin
                real_to_fp16 = 32'h00007C00;
            end
            else if (val == -1.0/0.0) begin
                real_to_fp16 = 32'h0000FC00;
            end
            else if (val == 0.0) begin
                real_to_fp16 = 32'h00000000;
            end
            else begin
                sign = (val < 0);
                abs_val = sign ? -val : val;
                
                exp_val = 0;
                mant = abs_val;
                while (mant >= 2.0) begin
                    mant = mant / 2.0;
                    exp_val = exp_val + 1;
                end
                while (mant < 1.0 && exp_val > -14) begin
                    mant = mant * 2.0;
                    exp_val = exp_val - 1;
                end
                
                if (exp_val < -14) begin
                    real_to_fp16 = {16'b0, sign, 15'b0};
                end
                else if (exp_val > 15) begin
                    real_to_fp16 = sign ? 32'h0000FC00 : 32'h00007C00;
                end
                else begin
                    exp = exp_val + 15;
                    frac = $rtoi((mant - 1.0) * $pow(2.0, 10.0));
                    real_to_fp16 = {16'b0, sign, exp, frac};
                end
            end
        end
    endfunction

    // ==========================================
    // TASK PARA VERIFICAR OPERACIONES
    // ==========================================
    task test_operation;
        input [127:0] desc;
        input real val_a, val_b;
        input is_sub;
        input is_single;
        input rnd_mode;
        real expected_real;
        reg [31:0] expected_fp;
        real result_real;
        real error;
        begin
            test_num = test_num + 1;
            
            mode_fp = is_single;
            op_sel = is_sub;
            round_mode = rnd_mode;
            
            // Convertir valores a formato float
            if (is_single) begin
                op_a = real_to_fp32(val_a);
                op_b = real_to_fp32(val_b);
            end else begin
                op_a = real_to_fp16(val_a);
                op_b = real_to_fp16(val_b);
            end
            
            // Calcular resultado esperado
            if (is_sub)
                expected_real = val_a - val_b;
            else
                expected_real = val_a + val_b;
            
            if (is_single)
                expected_fp = real_to_fp32(expected_real);
            else
                expected_fp = real_to_fp16(expected_real);
            
            #10;
            
            // Convertir resultado a real para comparar
            if (is_single)
                result_real = fp32_to_real(result);
            else
                result_real = fp16_to_real(result[15:0]);
            
            $display("\n=== Test %0d: %s ===", test_num, desc);
            $display("Mode: %s | Op: %s | Round: %s", 
                     is_single ? "SINGLE" : "HALF",
                     is_sub ? "SUB" : "ADD",
                     rnd_mode ? "+INF" : "NEAR");
            $display("Input:    %.10f %s %.10f", val_a, is_sub ? "-" : "+", val_b);
            $display("Expected: %.10f (0x%h)", expected_real, expected_fp);
            $display("Got:      %.10f (0x%h)", result_real, result);
            $display("Flags:    %b", flags);
            
            // Verificar resultado (con tolerancia para redondeo)
            if (expected_real != expected_real) begin // NaN
                if (result_real != result_real) begin
                    $display("✓ PASS - NaN detected correctly");
                    pass_count = pass_count + 1;
                end else begin
                    $display("✗ FAIL - Expected NaN");
                    fail_count = fail_count + 1;
                end
            end
            else if (expected_real == 1.0/0.0 || expected_real == -1.0/0.0) begin // Inf
                if (result_real == expected_real) begin
                    $display("✓ PASS - Infinity detected correctly");
                    pass_count = pass_count + 1;
                end else begin
                    $display("✗ FAIL - Expected Infinity");
                    fail_count = fail_count + 1;
                end
            end
            else begin
                error = (result_real - expected_real);
                if (error < 0) error = -error;
                
                // Tolerancia: 1 ULP aproximadamente
                if (result == expected_fp || error < 1e-6) begin
                    $display("✓ PASS");
                    pass_count = pass_count + 1;
                end else begin
                    $display("✗ FAIL - Error: %.10e", error);
                    fail_count = fail_count + 1;
                end
            end
        end
    endtask

    initial begin
        $dumpfile("addsub_floating.vcd");
        $dumpvars(0, tb_fpu_addsub);

        $display("\n========================================");
        $display("   FPU ADD/SUB ROBUST TESTBENCH");
        $display("========================================");

        // ==========================================
        // SINGLE PRECISION TESTS
        // ==========================================
        $display("\n--- SINGLE PRECISION BASIC OPERATIONS ---");
        test_operation("1.0 + 2.0", 1.0, 2.0, 0, 1, 0);
        test_operation("5.0 - 3.0", 5.0, 3.0, 1, 1, 0);
        test_operation("1.0 + 0.5", 1.0, 0.5, 0, 1, 0);
        test_operation("2.5 - 2.5", 2.5, 2.5, 1, 1, 0);
        test_operation("0.1 + 0.2", 0.1, 0.2, 0, 1, 0);
        test_operation("10.5 + 20.25", 10.5, 20.25, 0, 1, 0);
        
        $display("\n--- SINGLE PRECISION NEGATIVE NUMBERS ---");
        test_operation("-1.0 + -2.0", -1.0, -2.0, 0, 1, 0);
        test_operation("3.0 + -1.0", 3.0, -1.0, 0, 1, 0);
        test_operation("-5.0 - -3.0", -5.0, -3.0, 1, 1, 0);
        test_operation("1.0 - 2.0", 1.0, 2.0, 1, 1, 0);
        
        $display("\n--- SINGLE PRECISION SMALL/LARGE VALUES ---");
        test_operation("0.00001 + 0.00002", 0.00001, 0.00002, 0, 1, 0);
        test_operation("1000.0 + 2000.0", 1000.0, 2000.0, 0, 1, 0);
        test_operation("1e10 + 1e10", 1.0e10, 1.0e10, 0, 1, 0);
        
        $display("\n--- SINGLE PRECISION SPECIAL CASES ---");
        test_operation("0.0 + 0.0", 0.0, 0.0, 0, 1, 0);
        test_operation("1.0 + 0.0", 1.0, 0.0, 0, 1, 0);
        test_operation("0.0 - 0.0", 0.0, 0.0, 1, 1, 0);
        
        // ==========================================
        // HALF PRECISION TESTS
        // ==========================================
        $display("\n--- HALF PRECISION BASIC OPERATIONS ---");
        test_operation("HALF: 1.0 + 2.0", 1.0, 2.0, 0, 0, 0);
        test_operation("HALF: 3.0 - 1.0", 3.0, 1.0, 1, 0, 0);
        test_operation("HALF: 1.0 + 0.5", 1.0, 0.5, 0, 0, 0);
        test_operation("HALF: 4.0 + 4.0", 4.0, 4.0, 0, 0, 0);
        
        $display("\n--- HALF PRECISION NEGATIVE NUMBERS ---");
        test_operation("HALF: -1.0 + -2.0", -1.0, -2.0, 0, 0, 0);
        test_operation("HALF: 2.0 - 3.0", 2.0, 3.0, 1, 0, 0);
        
        $display("\n--- HALF PRECISION SMALL VALUES ---");
        test_operation("HALF: 0.5 + 0.25", 0.5, 0.25, 0, 0, 0);
        test_operation("HALF: 0.1 + 0.1", 0.1, 0.1, 0, 0, 0);
        
        // ==========================================
        // RESUMEN
        // ==========================================
        $display("\n========================================");
        $display("   TEST SUMMARY");
        $display("========================================");
        $display("Total tests:  %0d", test_num);
        $display("Passed:       %0d", pass_count);
        $display("Failed:       %0d", fail_count);
        $display("Success rate: %.1f%%", (pass_count * 100.0) / test_num);
        $display("========================================\n");
        
        if (fail_count == 0)
            $display("🎉 ALL TESTS PASSED! 🎉");
        else
            $display("⚠️  SOME TESTS FAILED");
        
        $finish;
    end

endmodule

Arch_Project.sim/sim_1/behav/xsim/addsub_floating.vcd
$date
   Fri Oct 10 17:26:05 2025
$end

$version
  2025.1.0
  $dumpfile ("addsub_floating.vcd") 
$end

$timescale
  1ps
$end

$scope module tb_fpu_addsub $end
$var reg 32 ! op_a [31:0] $end
$var reg 32 " op_b [31:0] $end
$var reg 1 # op_sel $end
$var reg 1 $ mode_fp $end
$var reg 1 % round_mode $end
$var wire 32 & result [31:0] $end
$var wire 5 ' flags [4:0] $end
$var integer 32 ( test_num [31:0] $end
$var integer 32 ) pass_count [31:0] $end
$var integer 32 * fail_count [31:0] $end
$scope module uut $end
$var wire 32 + op_a [31:0] $end
$var wire 32 , op_b [31:0] $end
$var wire 1 - op_sel $end
$var wire 1 . mode_fp $end
$var wire 1 / round_mode $end
$var reg 32 0 result [31:0] $end
$var reg 5 1 flags [4:0] $end
$var wire 32 2 a_val [31:0] $end
$var wire 32 3 b_val [31:0] $end
$var wire 1 4 sign_a $end
$var wire 1 5 sign_b $end
$var wire 8 6 exp_a [7:0] $end
$var wire 8 7 exp_b [7:0] $end
$var wire 23 8 frac_a [22:0] $end
$var wire 23 9 frac_b [22:0] $end
$var wire 24 : mant_a [23:0] $end
$var wire 24 ; mant_b [23:0] $end
$var wire 8 < exp_max [7:0] $end
$var wire 1 = is_nan_a $end
$var wire 1 > is_nan_b $end
$var wire 1 ? is_inf_a $end
$var wire 1 @ is_inf_b $end
$var wire 1 A is_zero_a $end
$var wire 1 B is_zero_b $end
$var reg 1 C effective_sub $end
$var wire 1 D sign_b_eff $end
$scope begin xd $end
$var reg 1 E sign_zero $end
$upscope $end
$scope begin xd2 $end
$var reg 8 F exp_diff [7:0] $end
$var reg 27 G mant_a_shifted [26:0] $end
$var reg 27 H mant_b_shifted [26:0] $end
$var reg 28 I mant_res [27:0] $end
$var reg 8 J exp_res [7:0] $end
$var reg 1 K sign_res $end
$var reg 1 L guard $end
$var reg 1 M round_bit $end
$var reg 1 N sticky $end
$var reg 24 O mant_final [23:0] $end
$var integer 32 P shift_count [31:0] $end
$upscope $end
$upscope $end
$scope function fp32_to_real $end
$var real 32 Q fp32_to_real $end
$var reg 32 R fp [31:0] $end
$var reg 1 S sign $end
$var reg 8 T exp [7:0] $end
$var reg 23 U frac [22:0] $end
$var real 32 V mant $end
$var integer 32 W exp_val [31:0] $end
$upscope $end
$scope function fp16_to_real $end
$var real 32 X fp16_to_real $end
$var reg 16 Y fp [15:0] $end
$var reg 1 Z sign $end
$var reg 5 [ exp [4:0] $end
$var reg 10 \ frac [9:0] $end
$var real 32 ] mant $end
$var integer 32 ^ exp_val [31:0] $end
$upscope $end
$scope function real_to_fp32 $end
$var reg 32 _ real_to_fp32 [31:0] $end
$var real 32 ` val $end
$var reg 1 a sign $end
$var reg 8 b exp [7:0] $end
$var reg 23 c frac [22:0] $end
$var real 32 d abs_val $end
$var real 32 e mant $end
$var integer 32 f exp_val [31:0] $end
$upscope $end
$scope function real_to_fp16 $end
$var reg 32 g real_to_fp16 [31:0] $end
$var real 32 h val $end
$var reg 1 i sign $end
$var reg 5 j exp [4:0] $end
$var reg 10 k frac [9:0] $end
$var real 32 l abs_val $end
$var real 32 m mant $end
$var integer 32 n exp_val [31:0] $end
$upscope $end
$scope task test_operation $end
$var reg 128 o desc [127:0] $end
$var real 32 p val_a $end
$var real 32 q val_b $end
$var reg 1 r is_sub $end
$var reg 1 s is_single $end
$var reg 1 t rnd_mode $end
$var real 32 u expected_real $end
$var reg 32 v expected_fp [31:0] $end
$var real 32 w result_real $end
$var real 32 x error $end
$upscope $end
$upscope $end
$enddefinitions $end

#0
$dumpvars
b111111100000000000000000000000 !
b1000000000000000000000000000000 "
0#
1$
0%
b1000000010000000000000000000000 &
b0 '
b1 (
b0 )
b0 *
b111111100000000000000000000000 +
b1000000000000000000000000000000 ,
0-
1.
0/
b1000000010000000000000000000000 0
b0 1
b111111100000000000000000000000 2
b1000000000000000000000000000000 3
04
05
b1111111 6
b10000000 7
b0 8
b0 9
b100000000000000000000000 :
b100000000000000000000000 ;
b11111111 <
0=
0>
0?
0@
0A
0B
0C
0D
xE
b1 F
b10000000000000000000000000 G
b100000000000000000000000000 H
b110000000000000000000000000 I
b10000000 J
0K
0L
0M
0N
b10000000000000000000000 O
b0 P
r0 Q
bx R
xS
bx T
bx U
r0 V
bx W
r0 X
bx Y
xZ
bx [
bx \
r0 ]
bx ^
b1000000010000000000000000000000 _
r3 `
0a
b10000000 b
b10000000000000000000000 c
r3 d
r1.5 e
b1 f
bx g
r0 h
xi
bx j
bx k
r0 l
r0 m
bx n
b1100010010111000110000001000000010101100100000001100100010111000110000 o
r1 p
r2 q
0r
1s
0t
r3 u
b1000000010000000000000000000000 v
r0 w
r0 x
$end

#10000
b1000000101000000000000000000000 !
b1000000010000000000000000000000 "
1#
b1000000000000000000000000000000 &
b10 (
b1 )
b1000000101000000000000000000000 +
b1000000010000000000000000000000 ,
1-
b1000000000000000000000000000000 0
b1000000101000000000000000000000 2
b1000000010000000000000000000000 3
b10000001 6
b1000000000000000000000 8
b10000000000000000000000 9
b101000000000000000000000 :
b110000000000000000000000 ;
1C
1D
b101000000000000000000000000 G
b11000000000000000000000000 H
b100000000000000000000000000 I
b10000000 J
b0 O
b1 P
r3 Q
b1000000010000000000000000000000 R
0S
b10000000 T
b10000000000000000000000 U
r1.5 V
b1 W
b1000000000000000000000000000000 _
r2 `
b10000000 b
b0 c
r2 d
r1 e
b1 f
b1101010010111000110000001000000010110100100000001100110010111000110000 o
r5 p
r3 q
1r
r2 u
b1000000000000000000000000000000 v
r3 w

#20000
b111111100000000000000000000000 !
b111111000000000000000000000000 "
0#
b111111110000000000000000000000 &
b11 (
b10 )
b111111100000000000000000000000 +
b111111000000000000000000000000 ,
0-
b111111110000000000000000000000 0
b111111100000000000000000000000 2
b111111000000000000000000000000 3
b1111111 6
b1111110 7
b0 8
b0 9
b100000000000000000000000 :
b100000000000000000000000 ;
0C
0D
b100000000000000000000000000 G
b10000000000000000000000000 H
b110000000000000000000000000 I
b1111111 J
b10000000000000000000000 O
b0 P
r2 Q
b1000000000000000000000000000000 R
b0 U
r1 V
b111111110000000000000000000000 _
r1.5 `
b1111111 b
b10000000000000000000000 c
r1.5 d
r1.5 e
b0 f
b1100010010111000110000001000000010101100100000001100000010111000110101 o
r1 p
r0.5 q
0r
r1.5 u
b111111110000000000000000000000 v
r2 w

#30000
b1000000001000000000000000000000 !
b1000000001000000000000000000000 "
1#
b0 &
b1000 '
b100 (
b11 )
b1000000001000000000000000000000 +
b1000000001000000000000000000000 ,
1-
b0 0
b1000 1
b1000000001000000000000000000000 2
b1000000001000000000000000000000 3
b10000000 6
b10000000 7
b1000000000000000000000 8
b1000000000000000000000 9
b101000000000000000000000 :
b101000000000000000000000 ;
1C
1D
b101000000000000000000000000 G
b101000000000000000000000000 H
b0 I
b10000000 J
r1.5 Q
b111111110000000000000000000000 R
b1111111 T
b10000000000000000000000 U
r1.5 V
b0 W
b0 _
r0 `
b10000000 b
b1000000000000000000000 c
r2.5 d
r1.25 e
b1 f
b1100100010111000110101001000000010110100100000001100100010111000110101 o
r2.5 p
r2.5 q
1r
r0 u
b0 v
r1.5 w

#40000
b111101110011001100110011001100 !
b111110010011001100110011001100 "
0#
b111110100110011001100110011001 &
b0 '
b101 (
b100 )
b111101110011001100110011001100 +
b111110010011001100110011001100 ,
0-
b111110100110011001100110011001 0
b0 1
b111101110011001100110011001100 2
b111110010011001100110011001100 3
b1111011 6
b1111100 7
b10011001100110011001100 8
b10011001100110011001100 9
b110011001100110011001100 :
b110011001100110011001100 ;
0C
0D
b11001100110011001100110000 G
b110011001100110011001100000 H
b100110011001100110011001000 I
b1111101 J
b110011001100110011001 O
r0 Q
b0 R
b0 T
b0 U
b111110100110011001100110011001 _
r0.3 `
b1111101 b
b110011001100110011001 c
r0.3 d
r1.2 e
b11111111111111111111111111111110 f
b1100000010111000110001001000000010101100100000001100000010111000110010 o
r0.1 p
r0.2 q
0r
r0.3 u
b111110100110011001100110011001 v
r0 w

#50000
b1000001001010000000000000000000 !
b1000001101000100000000000000000 "
b1000001111101100000000000000000 &
b110 (
b101 )
b1000001001010000000000000000000 +
b1000001101000100000000000000000 ,
b1000001111101100000000000000000 0
b1000001001010000000000000000000 2
b1000001101000100000000000000000 3
b10000010 6
b10000011 7
b1010000000000000000000 8
b1000100000000000000000 9
b101010000000000000000000 :
b101000100000000000000000 ;
b10101000000000000000000000 G
b101000100000000000000000000 H
b111101100000000000000000000 I
b10000011 J
b11101100000000000000000 O
r0.2999999821186066 Q
b111110100110011001100110011001 R
b1111101 T
b110011001100110011001 U
r1.199999928474426 V
b11111111111111111111111111111110 W
b1000001111101100000000000000000 _
r30.75 `
b10000011 b
b11101100000000000000000 c
r30.75 d
r1.921875 e
b100 f
b1100010011000000101110001101010010000000101011001000000011001000110000001011100011001000110101 o
r10.5 p
r20.25 q
r30.75 u
b1000001111101100000000000000000 v
r0.2999999821186066 w
r1.788139347702611e-08 x

#60000
b10111111100000000000000000000000 !
b11000000000000000000000000000000 "
b11000000010000000000000000000000 &
b111 (
b110 )
b10111111100000000000000000000000 +
b11000000000000000000000000000000 ,
b11000000010000000000000000000000 0
b10111111100000000000000000000000 2
b11000000000000000000000000000000 3
14
15
b1111111 6
b10000000 7
b0 8
b0 9
b100000000000000000000000 :
b100000000000000000000000 ;
1D
b10000000000000000000000000 G
b100000000000000000000000000 H
b110000000000000000000000000 I
b10000000 J
1K
b10000000000000000000000 O
r30.75 Q
b1000001111101100000000000000000 R
b10000011 T
b11101100000000000000000 U
r1.921875 V
b100 W
b11000000010000000000000000000000 _
r-3 `
1a
b10000000 b
b10000000000000000000000 c
r3 d
r1.5 e
b1 f
b10110100110001001011100011000000100000001010110010000000101101001100100010111000110000 o
r-1 p
r-2 q
r-3 u
b11000000010000000000000000000000 v
r30.75 w
r0 x

#70000
b1000000010000000000000000000000 !
b10111111100000000000000000000000 "
b1000000000000000000000000000000 &
b1000 (
b111 )
b1000000010000000000000000000000 +
b10111111100000000000000000000000 ,
b1000000000000000000000000000000 0
b1000000010000000000000000000000 2
b10111111100000000000000000000000 3
04
b10000000 6
b1111111 7
b10000000000000000000000 8
b110000000000000000000000 :
1C
b110000000000000000000000000 G
b10000000000000000000000000 H
b100000000000000000000000000 I
0K
b0 O
r-3 Q
b11000000010000000000000000000000 R
1S
b10000000 T
b10000000000000000000000 U
r1.5 V
b1 W
b1000000000000000000000000000000 _
r2 `
0a
b10000000 b
b0 c
r2 d
r1 e
b1 f
b110011001011100011000000100000001010110010000000101101001100010010111000110000 o
r3 p
r-1 q
r2 u
b1000000000000000000000000000000 v
r-3 w

#80000
b11000000101000000000000000000000 !
b11000000010000000000000000000000 "
1#
b11000000000000000000000000000000 &
b1001 (
b1000 )
b11000000101000000000000000000000 +
b11000000010000000000000000000000 ,
1-
b11000000000000000000000000000000 0
b11000000101000000000000000000000 2
b11000000010000000000000000000000 3
14
b10000001 6
b10000000 7
b1000000000000000000000 8
b10000000000000000000000 9
b101000000000000000000000 :
b110000000000000000000000 ;
0D
b101000000000000000000000000 G
b11000000000000000000000000 H
b100000000000000000000000000 I
b10000000 J
1K
b1 P
r2 Q
b1000000000000000000000000000000 R
0S
b0 U
r1 V
b11000000000000000000000000000000 _
r-2 `
1a
b10000000 b
b0 c
r2 d
r1 e
b1 f
b10110100110101001011100011000000100000001011010010000000101101001100110010111000110000 o
r-5 p
r-3 q
1r
r-2 u
b11000000000000000000000000000000 v
r2 w

